models/Alex_Net.py
models/CSP_DensNet.py
models/Le_Net.py
models/Mobile_Net.py
models/Res_Net.py
models/SK_Net.py
models/__init__.py
latest_cv_models-0.0.1.dist-info/LICENSE.txt
latest_cv_models-0.0.1.dist-info/METADATA
latest_cv_models-0.0.1.dist-info/WHEEL
latest_cv_models-0.0.1.dist-info/top_level.txt
latest_cv_models-0.0.1.dist-info/RECORD
