Metadata-Version: 2.1
Name: latest-cv-models
Version: 0.0.1
Summary: Latest Computer vision Models
Author: Ahmed Tolba
Author-email: atolba210@gmail.com
Classifier: License :: OSI Approved :: MIT License
Classifier: Operating System :: OS Independent
License-File: LICENSE.txt
